optracker/__init__.py
optracker/optracker.py
optracker/zerodata.py
optracker/data/__init__.py
optracker/data/face_models/dlib_face_recognition_resnet_model_v1.dat
optracker/data/face_models/mmod_human_face_detector.dat
optracker/data/face_models/shape_predictor_5_face_landmarks.dat
optracker/facerec/__init__.py
optracker/facerec/api.py
optracker/facerec/facerec.py
optracker/functions/__init__.py
optracker/functions/core_func.py
optracker/functions/db_func.py
optracker/functions/instagram_func.py
optracker/functions/side_func.py
optracker/igramscraper/__init__.py
optracker/igramscraper/endpoints.py
optracker/igramscraper/helper.py
optracker/igramscraper/instagram.py
optracker/igramscraper/session_manager.py
optracker/igramscraper/exception/__init__.py
optracker/igramscraper/exception/instagram_auth_exception.py
optracker/igramscraper/exception/instagram_exception.py
optracker/igramscraper/exception/instagram_not_found_exception.py
optracker/igramscraper/model/__init__.py
optracker/igramscraper/model/account.py
optracker/igramscraper/model/carousel_media.py
optracker/igramscraper/model/comment.py
optracker/igramscraper/model/initializer_model.py
optracker/igramscraper/model/location.py
optracker/igramscraper/model/media.py
optracker/igramscraper/model/story.py
optracker/igramscraper/model/tag.py
optracker/igramscraper/model/user_stories.py
optracker/igramscraper/two_step_verification/__init__.py
optracker/igramscraper/two_step_verification/console_verification.py
optracker/igramscraper/two_step_verification/two_step_verification_abstract_class.py
optracker-1.3.6.dist-info/LICENSE.md
optracker-1.3.6.dist-info/METADATA
optracker-1.3.6.dist-info/WHEEL
optracker-1.3.6.dist-info/entry_points.txt
optracker-1.3.6.dist-info/top_level.txt
optracker-1.3.6.dist-info/RECORD
