Metadata-Version: 2.1
Name: optracker
Version: 1.3.6
Summary: Scrapes medias, likes, followers from social media. Organize them in a database for more deeper analyze.
Home-page: https://github.com/suxSx/openSource-tracker
Author: suxSx
Author-email: marcuscrazy@gmail.com
Maintainer: suxSx
License: MIT
Keywords: scraper media social network mapper tracker instagram scrape like follow analyze
Platform: UNKNOWN
Classifier: Development Status :: 4 - Beta
Classifier: Environment :: Console
Classifier: Operating System :: OS Independent
Classifier: Intended Audience :: Developers
Classifier: Intended Audience :: Education
Classifier: Programming Language :: Python
Classifier: Programming Language :: Python :: 3.6
Classifier: Topic :: Education :: Testing
Classifier: License :: OSI Approved :: MIT License
Requires-Dist: python-slugify (==3.0.2)
Requires-Dist: unicodecsv (==0.14.1)
Requires-Dist: mysql-connector-python (==8.0.18)
Requires-Dist: cmake
Requires-Dist: Pillow
Requires-Dist: dlib (>=19.7)
